{
  "url": "https://api.github.com/repos/DataDog/datadog-lambda-java/releases/334524684",
  "assets_url": "https://api.github.com/repos/DataDog/datadog-lambda-java/releases/334524684/assets",
  "upload_url": "https://uploads.github.com/repos/DataDog/datadog-lambda-java/releases/334524684/assets{?name,label}",
  "html_url": "https://github.com/DataDog/datadog-lambda-java/releases/tag/v27",
  "id": 334524684,
  "author": {
    "login": "rithikanarayan",
    "id": 93233069,
    "node_id": "U_kgDOBY6frQ",
    "avatar_url": "https://avatars.githubusercontent.com/u/93233069?v=4",
    "gravatar_id": "",
    "url": "https://api.github.com/users/rithikanarayan",
    "html_url": "https://github.com/rithikanarayan",
    "followers_url": "https://api.github.com/users/rithikanarayan/followers",
    "following_url": "https://api.github.com/users/rithikanarayan/following{/other_user}",
    "gists_url": "https://api.github.com/users/rithikanarayan/gists{/gist_id}",
    "starred_url": "https://api.github.com/users/rithikanarayan/starred{/owner}{/repo}",
    "subscriptions_url": "https://api.github.com/users/rithikanarayan/subscriptions",
    "organizations_url": "https://api.github.com/users/rithikanarayan/orgs",
    "repos_url": "https://api.github.com/users/rithikanarayan/repos",
    "events_url": "https://api.github.com/users/rithikanarayan/events{/privacy}",
    "received_events_url": "https://api.github.com/users/rithikanarayan/received_events",
    "type": "User",
    "user_view_type": "public",
    "site_admin": false
  },
  "node_id": "RE_kwDODh3m084T8HEM",
  "tag_name": "v27",
  "target_commitish": "main",
  "name": "v27",
  "draft": false,
  "immutable": false,
  "prerelease": false,
  "created_at": "2026-06-04T18:16:49Z",
  "updated_at": "2026-06-04T18:18:13Z",
  "published_at": "2026-06-04T18:18:13Z",
  "assets": [

  ],
  "tarball_url": "https://api.github.com/repos/DataDog/datadog-lambda-java/tarball/v27",
  "zipball_url": "https://api.github.com/repos/DataDog/datadog-lambda-java/zipball/v27",
  "body": ">[!IMPORTANT]\r\n> dd-trace-java version [v1.63.0](https://github.com/DataDog/dd-trace-java/releases/tag/v1.63.0)\r\n\r\n## dd-trace-java layer ARN:\r\n\r\n### AWS Regions\r\n```\r\narn:aws:lambda:<AWS_REGION>:464622532012:layer:dd-trace-java:27\r\n```\r\n\r\n### AWS gov regions\r\n```\r\narn:aws-us-gov:lambda:<AWS_GOV_REGION>:002406178527:layer:dd-trace-java:27\r\n```\r\n\r\n**Full Changelog**: https://github.com/DataDog/dd-trace-java/compare/v1.57.0...v1.60.3"
}
