{
  "url": "https://api.github.com/repos/DataDog/dd-trace-js/releases/241005113",
  "assets_url": "https://api.github.com/repos/DataDog/dd-trace-js/releases/241005113/assets",
  "upload_url": "https://uploads.github.com/repos/DataDog/dd-trace-js/releases/241005113/assets{?name,label}",
  "html_url": "https://github.com/DataDog/dd-trace-js/releases/tag/v5.63.2",
  "id": 241005113,
  "author": {
    "login": "github-actions[bot]",
    "id": 41898282,
    "node_id": "MDM6Qm90NDE4OTgyODI=",
    "avatar_url": "https://avatars.githubusercontent.com/in/15368?v=4",
    "gravatar_id": "",
    "url": "https://api.github.com/users/github-actions%5Bbot%5D",
    "html_url": "https://github.com/apps/github-actions",
    "followers_url": "https://api.github.com/users/github-actions%5Bbot%5D/followers",
    "following_url": "https://api.github.com/users/github-actions%5Bbot%5D/following{/other_user}",
    "gists_url": "https://api.github.com/users/github-actions%5Bbot%5D/gists{/gist_id}",
    "starred_url": "https://api.github.com/users/github-actions%5Bbot%5D/starred{/owner}{/repo}",
    "subscriptions_url": "https://api.github.com/users/github-actions%5Bbot%5D/subscriptions",
    "organizations_url": "https://api.github.com/users/github-actions%5Bbot%5D/orgs",
    "repos_url": "https://api.github.com/users/github-actions%5Bbot%5D/repos",
    "events_url": "https://api.github.com/users/github-actions%5Bbot%5D/events{/privacy}",
    "received_events_url": "https://api.github.com/users/github-actions%5Bbot%5D/received_events",
    "type": "Bot",
    "user_view_type": "public",
    "site_admin": false
  },
  "node_id": "RE_kwDOBwapYs4OXXI5",
  "tag_name": "v5.63.2",
  "target_commitish": "v5.x",
  "name": "5.63.2",
  "draft": false,
  "immutable": false,
  "prerelease": false,
  "created_at": "2025-08-19T20:00:54Z",
  "updated_at": "2025-08-19T20:01:20Z",
  "published_at": "2025-08-19T20:01:20Z",
  "assets": [

  ],
  "tarball_url": "https://api.github.com/repos/DataDog/dd-trace-js/tarball/v5.63.2",
  "zipball_url": "https://api.github.com/repos/DataDog/dd-trace-js/zipball/v5.63.2",
  "body": "* \\[[`7de55f4efa`](https://github.com/DataDog/dd-trace-js/commit/7de55f4efa)] - **(SEMVER-PATCH)** **fix(llmobs)**: properly parse DD\\_TAGS onto span events' tags (Sam Brenner) [#6287](https://github.com/DataDog/dd-trace-js/pull/6287)"
}
